{
    "01_Distrito": "TULCAN||LOW",
    "02_NumeroCPIC": "EC56031181",
    "03_MRN": "CEC202420230069",
    "04_MSN": "0001",
    "05_TipoProcedimiento": "EXPORTACION",
    "06_EmpresaTransporte": "TRANSPORTES LOGITRANS-ACROS S.A.",
    "07_DepositoMercancia": "ALANDINO||LOW",
    "08_DirTransportista": "CALDERON NRO. 63-052 Y URUGUAY",
    "09_NroIdentificacion": "0491507748001",
    "10_PaisRemitente": "ECUADOR",
    "11_TipoIdRemitente": "RUC",
    "12_NroIdRemitente": "1792227577001",
    "13_NroCertSanitario": null,
    "14_NombreRemitente": "SACOS GALLARDO CIA. LTDA.",
    "15_DireccionRemitente": "ROCAFUERTE OE6-190 E IMBABURA",
    "16_PaisDestinatario": "COLOMBIA",
    "17_TipoIdDestinatario": "NIT",
    "18_NroIdDestinatario": "9016449550",
    "19_NombreDestinatario": "SACOSGALLARDO SAS",
    "20_DireccionDestinatario": "AK 80 2 51 BG 19 LC 14",
    "21_PaisConsignatario": "COLOMBIA",
    "22_TipoIdConsignatario": "NIT",
    "23_NroIdConsignatario": "9016449550",
    "24_NombreConsignatario": "SACOSGALLARDO SAS",
    "25_DireccionConsignatario": "AK 80 2 51 BG 19 LC 14",
    "26_NombreNotificado": "AGENCIA DE ADUANAS MERCANDINO LTDA. NIVEL 2",
    "27_DireccionNotificado": "CARRERA 7 N\u00ba 14-67, OFIC 202.",
    "28_PaisNotificado": "COLOMBIA",
    "29_PaisRecepcion": "ECUADOR",
    "30_CiudadRecepcion": "QUITO",
    "31_FechaRecepcion": "05-6-2024",
    "32_PaisEmbarque": "ECUADOR",
    "33_CiudadEmbarque": "QUITO",
    "34_FechaEmbarque": "05-6-2024",
    "35_PaisEntrega": "COLOMBIA",
    "36_CiudadEntrega": "IPIALES",
    "37_FechaEntrega": "05-7-2024",
    "38_CondicionesTransporte": "DIRECTO, SIN CAMBIO DEL CAMION",
    "39_CondicionesPago": "PAGO ANTICIPADO||LOW",
    "40_PesoNeto": "9748.70",
    "41_PesoBruto": "9855.20",
    "42_TotalBultos": "426",
    "43_Volumen": null,
    "44_OtraUnidad": null,
    "45_PrecioMercancias": "22413.26",
    "46_INCOTERM": "CPT",
    "47_TipoMoneda": "USD",
    "48_PaisMercancia": "COLOMBIA",
    "49_CiudadMercancia": "IPIALES",
    "50_GastosRemitente": "200.00",
    "51_MonedaRemitente": "USD",
    "52_GastosDestinatario": null,
    "53_MonedaDestinatario": null,
    "54_OtrosGastosRemitente": null,
    "55_OtrosMonedaRemitente": null,
    "56_OtrosGastosDestinatario": null,
    "57_OtrosMonedaDestinataio": null,
    "58_TotalRemitente": "200.00",
    "59_TotalDestinatario": null,
    "60_DocsRemitente": "FAC ELECTRO. N\u00ba 007-002-000004477",
    "61_FechaEmision": "05-6-2024",
    "62_PaisEmision": "ECUADOR",
    "63_CiudadEmision": "QUITO",
    "64_Instrucciones": null,
    "65_Observaciones": null,
    "66_Secuencia": "1",
    "67_TotalBultos": "426",
    "68_Embalaje": "BULTOS||LOW",
    "69_Marcas": "SIN MARCAS",
    "70_PesoNeto": "9748.70",
    "71_PesoBruto": "9855.20",
    "72_Volumen": null,
    "73_OtraUnidad": null,
    "74_Subpartida": null,
    "75_IMO1": null,
    "76_IMO2": null,
    "77_IMO2": null,
    "78_NroCertSanitario": null,
    "79_DescripcionCarga": "UNIDADES DE SACO MULTICOLOR 80X120\nUNIDADES DE SACO MALLA ROJO 60X85 \nUNIDADES DE SACO BLANCO 55X80 \nUNIDADES DE SACO BLANCO 60X90\nUNIDADES DE SACO NEGRO/VERDE 40X76\nUNIDADES DE SACO BICOLOR 50X60\nUNIDADES DE SACO MALLA BEIGE 60X85\nUNIDADES DE SACO MALLA MORADO 55X92\nVARIAS REFERENCIAS"
}